[
    {
        "name": "HTML",
        "text": "태그의 사용법을 어느 정도 알고 있음"
    },
    {
        "name": "JS",
        "text": "데이터를 뿌리거나 간단한 이벤트 등을 만들어 낼 수 있음"
    },
    {
        "name": "JSON",
        "text": "필요한 내용을 정리할 수 있음"
    },
    {
        "name": "JQUERY",
        "text": "조금 미숙하긴 하지만 간단한 사용법은 숙지하고 있음"
    },
    {
        "name": "NEXTJS",
        "text": "npm을 이용해 실행할 수 있고 프레임 구축 및 이벤트를 만들 수 있음"
    },
    {
        "name": "React",
        "text": "npm을 이용해 실행할 수 있고 프레임 구축 및 이벤트를 만들 수 있음"
    },
    {
        "name": "VUE",
        "text": "아직 미숙하지만 npm을 이용해 실행할 수 있고 프레임 구축 및 이벤트를 만들 수 있음"
    },
    {
        "name": "CSS",
        "text": "호버나 애프터 등을 사용할 수 있고 색을 입히거나 모양을 바꾸는 등의 사용 가능"
    },
    {
        "name": "SASS",
        "text": "키 프레임을 통한 애니메이션이나 믹스인, 변수 지정 등을 사용할 수 있음"
    },
    {
        "name": "MARIADB",
        "text": "서버주소 연결이나 설정입력 등을 해봤지만, 아직 미숙함"
    },
    {
        "name": "MYSQL",
        "text": "데이터를 저장할 테이블을 만들고 입력하거나 보낼 수 있음"
    },
    {
        "name": "API",
        "text": "필요한 API를 찾아 Axios를 사용해 내용을 꺼내올 수 있음"
    },
    {
        "name": "GIT",
        "text": "기본적인 pull과 push를 할 수 있음 브런치 생성이나 관련 명령어들은 아직 미숙함"
    },
    {
        "name": "FIGMA",
        "text": "대략적인 외형을 만들 수 있고 이미지를 저장하거나 크기 등을 확인할 수 있음"
    },
    {
        "name": "SWIPER",
        "text": "필요한 드래그나 슬라이드 기능을 찾아서 적용할 수 있음, 아직 미숙함"
    },
    {
        "name": "illustrator",
        "text": "도형을 가지고 간단한 모양을 만들 수 있음"
    }
]